cafe/__init__.py
cafe/consul/__init__.py
cafe/consul/agent.py
cafe/consul/kv.py
cafe/consul/lock.py
cafe/consul/semaphore.py
cafe/consul/session.py
python_cafe_consul-0.12.0.dist-info/DESCRIPTION.rst
python_cafe_consul-0.12.0.dist-info/METADATA
python_cafe_consul-0.12.0.dist-info/RECORD
python_cafe_consul-0.12.0.dist-info/WHEEL
python_cafe_consul-0.12.0.dist-info/metadata.json
python_cafe_consul-0.12.0.dist-info/top_level.txt
